infiniguard_api/__init__.py
infiniguard_api/__version__.py
infiniguard_api/api_server/__init__.py
infiniguard_api/api_server/config.py
infiniguard_api/api_server/infiniguard_api_app.py
infiniguard_api/common/__init__.py
infiniguard_api/common/const.py
infiniguard_api/common/messages.py
infiniguard_api/controller/__init__.py
infiniguard_api/controller/asynctask.py
infiniguard_api/controller/node.py
infiniguard_api/controller/user.py
infiniguard_api/controller/nas/__init__.py
infiniguard_api/controller/nas/adsdomain.py
infiniguard_api/controller/nas/nfssetting.py
infiniguard_api/controller/nas/share.py
infiniguard_api/controller/nas/shareadmin.py
infiniguard_api/controller/nas/sharehost.py
infiniguard_api/controller/nas/shareuser.py
infiniguard_api/controller/nas/smbsetting.py
infiniguard_api/controller/nas/workgroup.py
infiniguard_api/controller/network/__init__.py
infiniguard_api/controller/network/ethernet_ports.py
infiniguard_api/controller/network/host.py
infiniguard_api/controller/network/interfaces.py
infiniguard_api/controller/network/list_interface_xml.py
infiniguard_api/controller/network/misc.py
infiniguard_api/controller/network/netcfg.py
infiniguard_api/controller/network/static_routes.py
infiniguard_api/controller/network/tools.py
infiniguard_api/controller/ost/__init__.py
infiniguard_api/controller/ost/accentstats.py
infiniguard_api/controller/ost/lsu.py
infiniguard_api/controller/ost/ostair.py
infiniguard_api/controller/ost/ostsetting.py
infiniguard_api/controller/ost/storageserver.py
infiniguard_api/controller/ost/tlscertificate.py
infiniguard_api/controller/replication/__init__.py
infiniguard_api/controller/replication/ostmapping.py
infiniguard_api/controller/replication/sourcerep.py
infiniguard_api/controller/replication/targetrep.py
infiniguard_api/controller/vtl/__init__.py
infiniguard_api/controller/vtl/drive.py
infiniguard_api/controller/vtl/host.py
infiniguard_api/controller/vtl/host_mapping.py
infiniguard_api/controller/vtl/library.py
infiniguard_api-1.4.5.dist-info/METADATA
infiniguard_api-1.4.5.dist-info/WHEEL
infiniguard_api-1.4.5.dist-info/entry_points.txt
infiniguard_api-1.4.5.dist-info/namespace_packages.txt
infiniguard_api-1.4.5.dist-info/top_level.txt
infiniguard_api-1.4.5.dist-info/RECORD
