Metadata-Version: 2.1
Name: infiniguard-api
Version: 1.4.5
Summary: Infiniguard API
Home-page: UNKNOWN
Author: Maxim Kigel
Author-email: mkigel@infinidat.com
License: BSD
Platform: UNKNOWN
Classifier: Intended Audience :: Developers
Classifier: Intended Audience :: System Administrators
Classifier: License :: OSI Approved :: BSD License
Classifier: Operating System :: OS Independent
Classifier: Programming Language :: Python
Classifier: Topic :: Software Development :: Libraries :: Python Modules
Requires-Dist: apispec (==3.3.0)
Requires-Dist: configobj
Requires-Dist: ddt
Requires-Dist: dictdiffer
Requires-Dist: dnspython (==1.16.0)
Requires-Dist: flask-apispec (==0.9.0)
Requires-Dist: Flask (==1.1.2)
Requires-Dist: iba-install (>=2.6.7)
Requires-Dist: icmplib (==1.0.4)
Requires-Dist: infi.caching
Requires-Dist: ipaddress
Requires-Dist: logbook (==1.1.0)
Requires-Dist: marshmallow (==3.6.1)
Requires-Dist: pendulum (==1.4.2)
Requires-Dist: pyroute2 (==0.5.12)
Requires-Dist: represent
Requires-Dist: schematics (==2.0.1)
Requires-Dist: setuptools
Requires-Dist: sqlalchemy
Requires-Dist: structlog
Requires-Dist: webargs (==5.5.1)
Requires-Dist: wrapt
Requires-Dist: xmltodict
